prefect_gcp/__init__.py
prefect_gcp/_version.py
prefect_gcp/bigquery.py
prefect_gcp/cloud_storage.py
prefect_gcp/credentials.py
prefect_gcp/secret_manager.py
prefect_gcp/utilities.py
prefect_gcp/deployments/__init__.py
prefect_gcp/deployments/steps.py
prefect_gcp/experimental/__init__.py
prefect_gcp/experimental/decorators.py
prefect_gcp/experimental/bundles/__init__.py
prefect_gcp/experimental/bundles/execute.py
prefect_gcp/experimental/bundles/upload.py
prefect_gcp/models/__init__.py
prefect_gcp/models/cloud_run_v2.py
prefect_gcp/workers/__init__.py
prefect_gcp/workers/cloud_run.py
prefect_gcp/workers/cloud_run_v2.py
prefect_gcp/workers/vertex.py
prefect_gcp-0.6.14.dist-info/licenses/LICENSE
prefect_gcp-0.6.14.dist-info/METADATA
prefect_gcp-0.6.14.dist-info/WHEEL
prefect_gcp-0.6.14.dist-info/entry_points.txt
prefect_gcp-0.6.14.dist-info/top_level.txt
prefect_gcp-0.6.14.dist-info/RECORD
